{
  "snapshot": {
    "plantSlug": "ace-of-spades",
    "source": "soldcomps",
    "marketplace": "ebay.co.uk",
    "query": "Anthurium Ace of Spades",
    "checkedAt": "2026-06-28T20:04:23.031Z",
    "currency": "GBP",
    "rawResultCount": 240,
    "acceptedCount": 2,
    "rejectedCount": 238,
    "outlierCount": 0,
    "confidenceScore": "D",
    "minPrice": 34.80084,
    "p25Price": 42.36624,
    "medianPrice": 49.93164,
    "meanPrice": 49.93164,
    "trimmedMeanPrice": 49.93164,
    "p75Price": 57.49704,
    "maxPrice": 65.06244,
    "notes": ""
  },
  "stats": {
    "sampleSize": 2,
    "min": 34.80084,
    "max": 65.06244,
    "median": 49.93164,
    "mean": 49.93164,
    "p25": 42.36624,
    "p75": 57.49704,
    "iqr": 15.1308,
    "trimmedMean": 49.93164,
    "confidenceScore": "D",
    "rejectedCount": 238,
    "rejectionReasons": {},
    "outlierCount": 0
  },
  "acceptedListings": [
    {
      "title": "Anthurium Ace Of Spades X Papillilaminum 2.5\" pot, Fedex 2day*",
      "url": "https://www.ebay.com/itm/157434145333?nordt=true",
      "soldPrice": 21.93966,
      "totalPrice": 34.80084,
      "soldDate": "2026-05-22",
      "listingType": "whole_plant",
      "currency": "USD"
    },
    {
      "title": "Anthurium Ace Of Spades X Papillilaminum 4\" pot, Fedex 2day*",
      "url": "https://www.ebay.com/itm/167899247082?nordt=true",
      "soldPrice": 52.20126,
      "totalPrice": 65.06244,
      "soldDate": "2026-05-16",
      "listingType": "whole_plant",
      "currency": "USD"
    }
  ],
  "acceptedCount": 2,
  "rejectedCount": 238,
  "rejectionBreakdown": {
    "No accepted term found. Expected one of": [
      "anthurium roseospadix-rare central panamanian endemic aroid; one-off for 2026",
      "anthurium big bill plant in 6\" pot 22\" tall 31\" wide 20\" leaf large",
      "anthurium ace of hearts rare plant"
    ]
  }
}