{
  "plantSlug": "pallidiflorum",
  "checkedAt": "2026-06-28T16:46:44.967Z",
  "listings": [
    {
      "retailerSlug": "grow-tropicals",
      "retailerName": "Grow Tropicals",
      "title": "Anthurium Pallidiflorum (TC Plantlet) - Preorder",
      "productUrl": "https://growtropicals.com/products/anthurium-pallidiflorum-tc-plantlet-preorder",
      "priceGbp": 20.99,
      "inStock": false,
      "variantTitle": "TC Plant",
      "plantSizeLabel": "tc_plantlet",
      "sourceMethod": "shopify_json",
      "matchConfidence": 0.9
    },
    {
      "retailerSlug": "grow-tropicals",
      "retailerName": "Grow Tropicals",
      "title": "Anthurium pallidiflorum x panamense",
      "productUrl": "https://growtropicals.com/products/anthurium-pallidiflorum-x-panamense",
      "priceGbp": 145,
      "originalPriceGbp": 200,
      "inStock": false,
      "variantTitle": "6cm",
      "potSizeCm": 6,
      "plantSizeLabel": "established_plant",
      "sourceMethod": "shopify_json",
      "matchConfidence": 0.9
    },
    {
      "retailerSlug": "grow-tropicals",
      "retailerName": "Grow Tropicals",
      "title": "Anthurium pallidiflorum x panamense",
      "productUrl": "https://growtropicals.com/products/anthurium-pallidiflorum-x-panamense",
      "priceGbp": 180,
      "originalPriceGbp": 250,
      "inStock": false,
      "variantTitle": "9cm",
      "potSizeCm": 9,
      "plantSizeLabel": "established_plant",
      "sourceMethod": "shopify_json",
      "matchConfidence": 0.9
    },
    {
      "retailerSlug": "grow-tropicals",
      "retailerName": "Grow Tropicals",
      "title": "Anthurium pallidiflorum x panamense",
      "productUrl": "https://growtropicals.com/products/anthurium-pallidiflorum-x-panamense",
      "priceGbp": 170,
      "originalPriceGbp": 200,
      "inStock": false,
      "variantTitle": "9cm / #26",
      "potSizeCm": 9,
      "plantSizeLabel": "established_plant",
      "sourceMethod": "shopify_json",
      "matchConfidence": 0.9
    },
    {
      "retailerSlug": "grow-tropicals",
      "retailerName": "Grow Tropicals",
      "title": "Anthurium pallidiflorum",
      "productUrl": "https://growtropicals.com/products/anthurium-pallidiflorum",
      "priceGbp": 92.99,
      "inStock": false,
      "variantTitle": "10.5cm Hanging",
      "potSizeCm": 10.5,
      "plantSizeLabel": "established_plant",
      "sourceMethod": "shopify_json",
      "matchConfidence": 1
    },
    {
      "retailerSlug": "grow-tropicals",
      "retailerName": "Grow Tropicals",
      "title": "Anthurium pallidiflorum",
      "productUrl": "https://growtropicals.com/products/anthurium-pallidiflorum",
      "priceGbp": 65,
      "inStock": false,
      "variantTitle": "12cm",
      "potSizeCm": 12,
      "plantSizeLabel": "established_plant",
      "sourceMethod": "shopify_json",
      "matchConfidence": 1
    },
    {
      "retailerSlug": "grow-tropicals",
      "retailerName": "Grow Tropicals",
      "title": "Anthurium pallidiflorum",
      "productUrl": "https://growtropicals.com/products/anthurium-pallidiflorum",
      "priceGbp": 65,
      "inStock": false,
      "variantTitle": "9cm",
      "potSizeCm": 9,
      "plantSizeLabel": "established_plant",
      "sourceMethod": "shopify_json",
      "matchConfidence": 1
    },
    {
      "retailerSlug": "grow-tropicals",
      "retailerName": "Grow Tropicals",
      "title": "Anthurium pallidiflorum",
      "productUrl": "https://growtropicals.com/products/anthurium-pallidiflorum",
      "priceGbp": 45,
      "inStock": false,
      "variantTitle": "6cm",
      "potSizeCm": 6,
      "plantSizeLabel": "established_plant",
      "sourceMethod": "shopify_json",
      "matchConfidence": 1
    },
    {
      "retailerSlug": "grow-tropicals",
      "retailerName": "Grow Tropicals",
      "title": "Anthurium cf. pallidiflorum",
      "productUrl": "https://growtropicals.com/products/anthurium-cf-pallidiflorum",
      "priceGbp": 55,
      "inStock": false,
      "variantTitle": "9cm",
      "potSizeCm": 9,
      "plantSizeLabel": "established_plant",
      "sourceMethod": "shopify_json",
      "matchConfidence": 0.9
    },
    {
      "retailerSlug": "house-of-kojo",
      "retailerName": "House of Kojo",
      "title": "Anthurium pallidiflorum",
      "productUrl": "https://www.houseofkojo.com/products/anthurium-pallidiflorum",
      "priceGbp": 92.99,
      "inStock": false,
      "variantTitle": "10.5cm Hanging",
      "potSizeCm": 10.5,
      "plantSizeLabel": "established_plant",
      "sourceMethod": "shopify_json",
      "matchConfidence": 1
    },
    {
      "retailerSlug": "house-of-kojo",
      "retailerName": "House of Kojo",
      "title": "Anthurium pallidiflorum",
      "productUrl": "https://www.houseofkojo.com/products/anthurium-pallidiflorum",
      "priceGbp": 65,
      "inStock": false,
      "variantTitle": "12cm",
      "potSizeCm": 12,
      "plantSizeLabel": "established_plant",
      "sourceMethod": "shopify_json",
      "matchConfidence": 1
    },
    {
      "retailerSlug": "house-of-kojo",
      "retailerName": "House of Kojo",
      "title": "Anthurium pallidiflorum",
      "productUrl": "https://www.houseofkojo.com/products/anthurium-pallidiflorum",
      "priceGbp": 65,
      "inStock": false,
      "variantTitle": "9cm",
      "potSizeCm": 9,
      "plantSizeLabel": "established_plant",
      "sourceMethod": "shopify_json",
      "matchConfidence": 1
    },
    {
      "retailerSlug": "house-of-kojo",
      "retailerName": "House of Kojo",
      "title": "Anthurium pallidiflorum",
      "productUrl": "https://www.houseofkojo.com/products/anthurium-pallidiflorum",
      "priceGbp": 45,
      "inStock": false,
      "variantTitle": "6cm",
      "potSizeCm": 6,
      "plantSizeLabel": "established_plant",
      "sourceMethod": "shopify_json",
      "matchConfidence": 1
    },
    {
      "retailerSlug": "sprouts-of-bristol",
      "retailerName": "Sprouts of Bristol",
      "title": "Anthurium vittarifolium – Strap Leaf Anthurium",
      "productUrl": "https://sproutsofbristol.co.uk/products/anthurium-vittarifolium-strap-leaf-anthurium",
      "priceGbp": 39,
      "originalPriceGbp": 52,
      "inStock": true,
      "variantTitle": "14cm",
      "potSizeCm": 14,
      "plantSizeLabel": "established_plant",
      "sourceMethod": "shopify_json",
      "matchConfidence": 0.9
    }
  ],
  "statsByType": {
    "all": {
      "min": 39,
      "max": 39,
      "median": 39,
      "mean": 39,
      "trimmedMean": 39,
      "p25": 39,
      "p75": 39,
      "count": 1
    },
    "established_plant": {
      "min": 39,
      "max": 39,
      "median": 39,
      "mean": 39,
      "trimmedMean": 39,
      "p25": 39,
      "p75": 39,
      "count": 1
    }
  }
}